{
  "tasks": [
    {
      "title": "aaaaa",
      "notes": "aaaaa",
      "length": 2,
      "start_date": "2023-06-21",
      "period": 2,
      "strict_recurrence": false,
      "created_date": "2023-06-21",
      "last_completed": "2023-07-19"
    },
    {
      "title": "this is a task",
      "notes": "these are notes",
      "length": 1,
      "start_date": "2023-06-22",
      "period": 1,
      "strict_recurrence": false,
      "created_date": "2023-06-22",
      "last_completed": null
    },
    {
      "title": "iirnets",
      "notes": "nesri",
      "length": 0,
      "start_date": "2023-06-23",
      "period": 0,
      "strict_recurrence": true,
      "created_date": "2023-06-23",
      "last_completed": null
    },
    {
      "title": "eeeee",
      "notes": "stnrei",
      "length": 0,
      "start_date": "2023-07-17",
      "period": 0,
      "strict_recurrence": false,
      "created_date": "2023-07-17",
      "last_completed": null
    }
  ],
  "tasklists": [
    {
      "title": "2023-06-23 19:51:32.661565",
      "tasks": {
        "iirnets": 0,
        "aaaaa": 0,
        "this is a task": 0
      }
    }
  ],
  "current_tasklist": null
}